Metadata-Version: 2.1
Name: py-serpro-biodata
Version: 1.0.0
Summary: Python lib não oficial do serviço BIOValid do SERPRO no Brasil
Home-page: https://github.com/juliosmelo/py_serpro_biodata
Author: Julio Melo
Author-email: juliocsmelo@gmail.com
License: MIT
Platform: UNKNOWN
Classifier: Development Status :: 5 - Production/Stable
Classifier: Intended Audience :: Developers
Classifier: License :: OSI Approved :: MIT License
Classifier: Natural Language :: Portuguese
Classifier: Operating System :: POSIX :: Linux
Classifier: Programming Language :: Python
Classifier: Programming Language :: Python :: 3
Classifier: Programming Language :: Python :: 3.4
Classifier: Programming Language :: Python :: 3.5
Classifier: Programming Language :: Python :: 3.6
Classifier: Topic :: System :: Installation/Setup
